[
  {
    "$type": "VendingMachine.Drink, VendingMachine",
    "description": "A Softdrink",
    "price": 15,
    "name": "Cola"
  },
  {
    "$type": "VendingMachine.Drink, VendingMachine",
    "description": "A Softdrink",
    "price": 15,
    "name": "Fanta"
  },
  {
    "$type": "VendingMachine.Drink, VendingMachine",
    "description": "A hot beverage.",
    "price": 13,
    "name": "Tea"
  },
  {
    "$type": "VendingMachine.Drink, VendingMachine",
    "description": "A hot black beverage.",
    "price": 20,
    "name": "Coffee"
  },
  {
    "$type": "VendingMachine.Drink, VendingMachine",
    "description": "Plain Water.",
    "price": 5,
    "name": "Water"
  },
  {
    "$type": "VendingMachine.Snack, VendingMachine",
    "description": "A Bag of potato chips.",
    "price": 10,
    "name": "Chips"
  },
  {
    "$type": "VendingMachine.Snack, VendingMachine",
    "description": "A Bag of peanuts.",
    "price": 10,
    "name": "Peanuts"
  },
  {
    "$type": "VendingMachine.Food, VendingMachine",
    "description": "A square pizza.",
    "price": 15,
    "name": "PanPizza"
  },
  {
    "$type": "VendingMachine.Food, VendingMachine",
    "description": "A plain hamburger.",
    "price": 20,
    "name": "Burger"
  },
  {
    "$type": "VendingMachine.Food, VendingMachine",
    "description": "A awesome hamburger.",
    "price": 15,
    "name": "Bacon Burger"
  },
  {
    "$type": "VendingMachine.Food, VendingMachine",
    "description": "Contains \"high-energy plankton\".",
    "price": 15,
    "name": "Soylent Green"
  }
]